diaspy/__init__.py
diaspy/connection.py
diaspy/conversations.py
diaspy/errors.py
diaspy/models.py
diaspy/notifications.py
diaspy/people.py
diaspy/search.py
diaspy/settings.py
diaspy/streams.py
diaspy_api-0.6.0.dist-info/LICENSE
diaspy_api-0.6.0.dist-info/METADATA
diaspy_api-0.6.0.dist-info/WHEEL
diaspy_api-0.6.0.dist-info/top_level.txt
diaspy_api-0.6.0.dist-info/RECORD
